kotlin version: 2.2.0
error message: org.jetbrains.kotlin.codegen.CompilationException: Back-end (JVM) Internal error: Couldn't transform method node:
getListCellRendererComponent (Ljavax/swing/JList;Ljava/lang/Object;IZZ)Ljava/awt/Component;:
  @Lorg/jetbrains/annotations/NotNull;() // invisible
    // annotable parameter count: 5 (visible)
    // annotable parameter count: 5 (invisible)
    @Lorg/jetbrains/annotations/Nullable;() // invisible, parameter 0
    @Lorg/jetbrains/annotations/Nullable;() // invisible, parameter 1
   L0
    ALOAD 0
   L1
    LINENUMBER 30 L1
    ALOAD 1
    ALOAD 2
    ILOAD 3
    ILOAD 4
    ILOAD 5
    INVOKESPECIAL com/intellij/ui/SimpleListCellRenderer.getListCellRendererComponent (Ljavax/swing/JList;Ljava/lang/Object;IZZ)Ljava/awt/Component;
    ASTORE 7
    NOP
   L2
    ALOAD 7
    CHECKCAST java/awt/Component
    ASTORE 8
    INVOKESTATIC kotlin/jvm/internal/InlineMarker.beforeInlineCall ()V
   L3
    ICONST_0
    ISTORE 9
   L4
    LINENUMBER 31 L4
    ALOAD 0
    GETFIELD com/github/pushpavel/autocp/common/ui/swing/TileCellRenderer.padding : I
    ALOAD 0
    GETFIELD com/github/pushpavel/autocp/common/ui/swing/TileCellRenderer.padding : I
    ALOAD 0
    GETFIELD com/github/pushpavel/autocp/common/ui/swing/TileCellRenderer.padding : I
    ALOAD 0
    GETFIELD com/github/pushpavel/autocp/common/ui/swing/TileCellRenderer.padding : I
    INVOKESTATIC javax/swing/BorderFactory.createEmptyBorder (IIII)Ljavax/swing/border/Border;
    ASTORE 10
   L5
    LINENUMBER 32 L5
    ALOAD 0
    ALOAD 0
    INVOKEVIRTUAL com/github/pushpavel/autocp/common/ui/swing/TileCellRenderer.getBorder ()Ljavax/swing/border/Border;
    ALOAD 10
    INVOKESTATIC javax/swing/BorderFactory.createCompoundBorder (Ljavax/swing/border/Border;Ljavax/swing/border/Border;)Ljavax/swing/border/CompoundBorder;
    CHECKCAST javax/swing/border/Border
    INVOKEVIRTUAL com/github/pushpavel/autocp/common/ui/swing/TileCellRenderer.setBorder (Ljavax/swing/border/Border;)V
   L6
    LINENUMBER 33 L6
    NOP
    GOTO L7
   L7
    GETSTATIC kotlin/Unit.INSTANCE : Lkotlin/Unit;
    INVOKESTATIC kotlin/jvm/internal/InlineMarker.afterInlineCall ()V
   L8
    LINENUMBER 30 L8
    POP
    ALOAD 7
    NOP
    GOTO L9
   L9
    LINENUMBER 30 L9
    ASTORE 6
   L10
    ALOAD 6
    LDC "apply(...)"
    INVOKESTATIC kotlin/jvm/internal/Intrinsics.checkNotNullExpressionValue (Ljava/lang/Object;Ljava/lang/String;)V
    ALOAD 6
   L11
    CHECKCAST java/awt/Component
    ARETURN
   L12
    NOP
   L13
    LOCALVARIABLE $i$a$-apply-TileCellRenderer$getListCellRendererComponent$1 I L4 L7 9
    LOCALVARIABLE paddingBorder Ljavax/swing/border/Border; L5 L7 10
    LOCALVARIABLE $this$getListCellRendererComponent_u24lambda_u240 Ljava/awt/Component; L3 L7 8
    LOCALVARIABLE this Lcom/github/pushpavel/autocp/common/ui/swing/TileCellRenderer; L0 L13 0
    LOCALVARIABLE list Ljavax/swing/JList; L0 L13 1
    LOCALVARIABLE value Ljava/lang/Object; L0 L13 2
    LOCALVARIABLE index I L0 L13 3
    LOCALVARIABLE isSelected Z L0 L13 4
    LOCALVARIABLE cellHasFocus Z L0 L13 5
    MAXSTACK = 6
    MAXLOCALS = 11

File is unknown
The root cause java.lang.OutOfMemoryError was thrown at: org.jetbrains.org.objectweb.asm.tree.analysis.Frame.<init>(Frame.java:96)
	at org.jetbrains.kotlin.codegen.TransformationMethodVisitor.visitEnd(TransformationMethodVisitor.kt:89)
	at org.jetbrains.org.objectweb.asm.MethodVisitor.visitEnd(MethodVisitor.java:796)
	at org.jetbrains.org.objectweb.asm.tree.MethodNode.accept(MethodNode.java:770)
	at org.jetbrains.kotlin.backend.jvm.codegen.ClassCodegen.generateMethod(ClassCodegen.kt:469)
	at org.jetbrains.kotlin.backend.jvm.codegen.ClassCodegen.generate(ClassCodegen.kt:164)
	at org.jetbrains.kotlin.backend.jvm.JvmIrCodegenFactory.generateFile(JvmIrCodegenFactory.kt:419)
	at org.jetbrains.kotlin.backend.jvm.JvmIrCodegenFactory.invokeCodegen(JvmIrCodegenFactory.kt:388)
	at org.jetbrains.kotlin.cli.jvm.compiler.KotlinToJVMBytecodeCompiler.runCodegen$cli(KotlinToJVMBytecodeCompiler.kt:432)
	at org.jetbrains.kotlin.cli.pipeline.jvm.JvmBackendPipelinePhase.executePhase(JvmBackendPipelinePhase.kt:95)
	at org.jetbrains.kotlin.cli.pipeline.jvm.JvmBackendPipelinePhase.executePhase(JvmBackendPipelinePhase.kt:36)
	at org.jetbrains.kotlin.cli.pipeline.jvm.JvmBackendPipelinePhase.executePhase(JvmBackendPipelinePhase.kt:29)
	at org.jetbrains.kotlin.cli.pipeline.PipelinePhase.phaseBody(PipelinePhase.kt:68)
	at org.jetbrains.kotlin.cli.pipeline.PipelinePhase.phaseBody(PipelinePhase.kt:58)
	at org.jetbrains.kotlin.config.phaser.NamedCompilerPhase.invoke(CompilerPhase.kt:102)
	at org.jetbrains.kotlin.backend.common.phaser.CompositePhase.invoke(PhaseBuilders.kt:22)
	at org.jetbrains.kotlin.config.phaser.CompilerPhaseKt.invokeToplevel(CompilerPhase.kt:53)
	at org.jetbrains.kotlin.cli.pipeline.AbstractCliPipeline.runPhasedPipeline(AbstractCliPipeline.kt:109)
	at org.jetbrains.kotlin.cli.pipeline.AbstractCliPipeline.execute(AbstractCliPipeline.kt:68)
	at org.jetbrains.kotlin.cli.jvm.K2JVMCompiler.doExecutePhased(K2JVMCompiler.kt:78)
	at org.jetbrains.kotlin.cli.jvm.K2JVMCompiler.doExecutePhased(K2JVMCompiler.kt:44)
	at org.jetbrains.kotlin.cli.common.CLICompiler.execImpl(CLICompiler.kt:90)
	at org.jetbrains.kotlin.cli.common.CLICompiler.exec(CLICompiler.kt:352)
	at org.jetbrains.kotlin.incremental.IncrementalJvmCompilerRunnerBase.runCompiler(IncrementalJvmCompilerRunnerBase.kt:175)
	at org.jetbrains.kotlin.incremental.IncrementalJvmCompilerRunnerBase.runCompiler(IncrementalJvmCompilerRunnerBase.kt:38)
	at org.jetbrains.kotlin.incremental.IncrementalCompilerRunner.doCompile(IncrementalCompilerRunner.kt:504)
	at org.jetbrains.kotlin.incremental.IncrementalCompilerRunner.compileImpl(IncrementalCompilerRunner.kt:421)
	at org.jetbrains.kotlin.incremental.IncrementalCompilerRunner.tryCompileIncrementally$lambda$10$compile(IncrementalCompilerRunner.kt:254)
	at org.jetbrains.kotlin.incremental.IncrementalCompilerRunner.tryCompileIncrementally(IncrementalCompilerRunner.kt:272)
	at org.jetbrains.kotlin.incremental.IncrementalCompilerRunner.compile(IncrementalCompilerRunner.kt:124)
	at org.jetbrains.kotlin.daemon.CompileServiceImplBase.execIncrementalCompiler(CompileServiceImpl.kt:679)
	at org.jetbrains.kotlin.daemon.CompileServiceImplBase.access$execIncrementalCompiler(CompileServiceImpl.kt:93)
	at org.jetbrains.kotlin.daemon.CompileServiceImpl.compile(CompileServiceImpl.kt:1806)
	at java.base/jdk.internal.reflect.DirectMethodHandleAccessor.invoke(DirectMethodHandleAccessor.java:104)
	at java.base/java.lang.reflect.Method.invoke(Method.java:565)
	at java.rmi/sun.rmi.server.UnicastServerRef.dispatch(UnicastServerRef.java:351)
	at java.rmi/sun.rmi.transport.Transport.serviceCall(Transport.java:166)
	at java.rmi/sun.rmi.transport.tcp.TCPTransport.handleMessages(TCPTransport.java:543)
	at java.rmi/sun.rmi.transport.tcp.TCPTransport$ConnectionHandler.run0(TCPTransport.java:744)
	at java.rmi/sun.rmi.transport.tcp.TCPTransport$ConnectionHandler.run(TCPTransport.java:623)
	at java.base/java.util.concurrent.ThreadPoolExecutor.runWorker(ThreadPoolExecutor.java:1095)
	at java.base/java.util.concurrent.ThreadPoolExecutor$Worker.run(ThreadPoolExecutor.java:619)
	at java.base/java.lang.Thread.run(Thread.java:1447)
Caused by: java.lang.OutOfMemoryError: GC overhead limit exceeded
	at org.jetbrains.org.objectweb.asm.tree.analysis.Frame.<init>(Frame.java:96)
	at org.jetbrains.kotlin.codegen.optimization.fixStack.FixStackAnalyzer$FixStackFrame.<init>(FixStackAnalyzer.kt:98)
	at org.jetbrains.kotlin.codegen.optimization.fixStack.FixStackAnalyzer.analyzer$lambda$0(FixStackAnalyzer.kt:46)
	at org.jetbrains.kotlin.codegen.optimization.fixStack.FixStackAnalyzer$$Lambda/0x0000000e01833de0.invoke(Unknown Source)
	at org.jetbrains.kotlin.codegen.optimization.common.FastAnalyzer.fastMergeControlFlowEdge(FastAnalyzer.kt:256)
	at org.jetbrains.kotlin.codegen.optimization.common.FastAnalyzer.mergeControlFlowEdge(FastAnalyzer.kt:214)
	at org.jetbrains.kotlin.codegen.optimization.common.FastAnalyzer.processControlFlowEdge(FastAnalyzer.kt:208)
	at org.jetbrains.kotlin.codegen.optimization.common.FastAnalyzer.processControlFlowEdge$default(FastAnalyzer.kt:206)
	at org.jetbrains.kotlin.codegen.optimization.common.FastAnalyzer.visitOpInsn(FastAnalyzer.kt:292)
	at org.jetbrains.kotlin.codegen.optimization.common.FastAnalyzer.visitMeaningfulInstruction(FastAnalyzer.kt:281)
	at org.jetbrains.kotlin.codegen.optimization.common.FastAnalyzer.analyzeInstruction(FastAnalyzer.kt:113)
	at org.jetbrains.kotlin.codegen.optimization.common.FastAnalyzer.analyzeMainLoop(FastAnalyzer.kt:74)
	at org.jetbrains.kotlin.codegen.optimization.common.FastAnalyzer.analyze(FastAnalyzer.kt:53)
	at org.jetbrains.kotlin.codegen.optimization.fixStack.FixStackAnalyzer.analyze(FixStackAnalyzer.kt:60)
	at org.jetbrains.kotlin.codegen.optimization.fixStack.FixStackMethodTransformer.analyzeAndTransformBreakContinueGotos(FixStackMethodTransformer.kt:55)
	at org.jetbrains.kotlin.codegen.optimization.fixStack.FixStackMethodTransformer.transform(FixStackMethodTransformer.kt:44)
	at org.jetbrains.kotlin.codegen.optimization.transformer.CompositeMethodTransformer.transform(CompositeMethodTransformer.kt:25)
	at org.jetbrains.kotlin.codegen.optimization.transformer.CompositeMethodTransformer.transform(CompositeMethodTransformer.kt:25)
	at org.jetbrains.kotlin.codegen.optimization.OptimizationMethodVisitor.performTransformations(OptimizationMethodVisitor.kt:70)
	at org.jetbrains.kotlin.codegen.TransformationMethodVisitor.visitEnd(TransformationMethodVisitor.kt:67)
	at org.jetbrains.org.objectweb.asm.MethodVisitor.visitEnd(MethodVisitor.java:796)
	at org.jetbrains.org.objectweb.asm.tree.MethodNode.accept(MethodNode.java:770)
	at org.jetbrains.kotlin.backend.jvm.codegen.ClassCodegen.generateMethod(ClassCodegen.kt:469)
	at org.jetbrains.kotlin.backend.jvm.codegen.ClassCodegen.generate(ClassCodegen.kt:164)
	at org.jetbrains.kotlin.backend.jvm.JvmIrCodegenFactory.generateFile(JvmIrCodegenFactory.kt:419)
	at org.jetbrains.kotlin.backend.jvm.JvmIrCodegenFactory.invokeCodegen(JvmIrCodegenFactory.kt:388)
	at org.jetbrains.kotlin.cli.jvm.compiler.KotlinToJVMBytecodeCompiler.runCodegen$cli(KotlinToJVMBytecodeCompiler.kt:432)
	at org.jetbrains.kotlin.cli.pipeline.jvm.JvmBackendPipelinePhase.executePhase(JvmBackendPipelinePhase.kt:95)
	at org.jetbrains.kotlin.cli.pipeline.jvm.JvmBackendPipelinePhase.executePhase(JvmBackendPipelinePhase.kt:36)
	at org.jetbrains.kotlin.cli.pipeline.jvm.JvmBackendPipelinePhase.executePhase(JvmBackendPipelinePhase.kt:29)
	at org.jetbrains.kotlin.cli.pipeline.PipelinePhase.phaseBody(PipelinePhase.kt:68)
	at org.jetbrains.kotlin.cli.pipeline.PipelinePhase.phaseBody(PipelinePhase.kt:58)


